CustomLogger.py
ScraperLib.py
__init__.py
scraper_lib_rmp-0.2.295.dist-info/METADATA
scraper_lib_rmp-0.2.295.dist-info/WHEEL
scraper_lib_rmp-0.2.295.dist-info/top_level.txt
scraper_lib_rmp-0.2.295.dist-info/RECORD
