Metadata-Version: 2.4
Name: Scraper-Lib-RMP
Version: 0.2.295
Summary: Add your description here
Author-email: Rodrigo Monteiro Pereira <rmonteiropereira1@gmail.com>
Requires-Python: >=3.12
Requires-Dist: beautifulsoup4>=4.13.4
Requires-Dist: colorama>=0.4.6
Requires-Dist: filelock>=3.18.0
Requires-Dist: matplotlib>=3.10.1
Requires-Dist: mypy>=1.15.0
Requires-Dist: myst-parser>=4.0.1
Requires-Dist: portalocker>=3.1.1
Requires-Dist: prettyprint>=0.1.5
Requires-Dist: ray>=2.44.1
Requires-Dist: requests>=2.32.3
Requires-Dist: rich>=14.0.0
Requires-Dist: ruff>=0.11.6
Requires-Dist: tqdm>=4.67.1
Requires-Dist: virtualenv>=20.30.0
